chun_codes/__init__.py
chun_codes/cardelli.py
chun_codes-0.8.1.dist-info/LICENSE
chun_codes-0.8.1.dist-info/METADATA
chun_codes-0.8.1.dist-info/WHEEL
chun_codes-0.8.1.dist-info/top_level.txt
chun_codes-0.8.1.dist-info/RECORD
