Metadata-Version: 2.1
Name: chun-codes
Version: 0.8.1
Summary: Set of Python 2.7 and 3.xx codes used in astrochun's codes
Home-page: https://github.com/astrochun/chun_codes
Author: Chun Ly
Author-email: astro.chun@gmail.com
License: MIT
Platform: UNKNOWN
Classifier: Development Status :: 4 - Beta
Classifier: Programming Language :: Python :: 2.7
Classifier: Programming Language :: Python :: 3.7
Classifier: Programming Language :: Python :: 3.8
Classifier: Programming Language :: Python :: 3.9
Requires-Python: >=3.7
Requires-Dist: numpy
Requires-Dist: pdfmerge ; python_version == "2.7"
Requires-Dist: matplotlib (==2.2.5) ; python_version == "2.7"
Requires-Dist: astropy (==2.0.16) ; python_version == "2.7"
Requires-Dist: matplotlib ; python_version >= "3.0"
Requires-Dist: astropy ; python_version >= "3.0"
